{
	"info": {
		"_postman_id": "eb463897-cf96-4358-9fd1-de236934f916",
		"name": "WeatherForecast/YehorSlipchenko",
		"schema": "https://schema.getpostman.com/json/collection/v2.0.0/collection.json",
		"_exporter_id": "26037403"
	},
	"item": [
		{
			"name": "GetLondonWeather (present)",
			"event": [
				{
					"listen": "test",
					"script": {
						"exec": [
							"pm.test(\"Status code is 200\", function () {",
							"    pm.response.to.have.status(200);",
							"});"
						],
						"type": "text/javascript",
						"packages": {}
					}
				}
			],
			"request": {
				"method": "GET",
				"header": [],
				"url": {
					"raw": "https://weather-api-07252024.azurewebsites.net/WeatherForecast?Date=07.25.2024&City=London&Country=United Kingdom",
					"protocol": "https",
					"host": [
						"weather-api-07252024",
						"azurewebsites",
						"net"
					],
					"path": [
						"WeatherForecast"
					],
					"query": [
						{
							"key": "Date",
							"value": "07.25.2024"
						},
						{
							"key": "City",
							"value": "London"
						},
						{
							"key": "Country",
							"value": "United Kingdom"
						}
					]
				},
				"description": "This is a GET request and it is used to \"get\" data from an endpoint. There is no request body for a GET request, but you can use query parameters to help specify the resource you want data on (e.g., in this request, we have `id=1`).\n\nA successful GET response will have a `200 OK` status, and should include some kind of response body - for example, HTML web content or JSON data."
			},
			"response": []
		},
		{
			"name": "GetLondonWeather (future)",
			"event": [
				{
					"listen": "test",
					"script": {
						"exec": [
							"pm.test(\"Status code is 200\", function () {",
							"    pm.response.to.have.status(200);",
							"});"
						],
						"type": "text/javascript",
						"packages": {}
					}
				}
			],
			"request": {
				"method": "GET",
				"header": [],
				"url": {
					"raw": "https://weather-api-07252024.azurewebsites.net/WeatherForecast?Date=07.30.2024&City=London&Country=United Kingdom",
					"protocol": "https",
					"host": [
						"weather-api-07252024",
						"azurewebsites",
						"net"
					],
					"path": [
						"WeatherForecast"
					],
					"query": [
						{
							"key": "Date",
							"value": "07.30.2024"
						},
						{
							"key": "City",
							"value": "London"
						},
						{
							"key": "Country",
							"value": "United Kingdom"
						}
					]
				},
				"description": "This is a GET request and it is used to \"get\" data from an endpoint. There is no request body for a GET request, but you can use query parameters to help specify the resource you want data on (e.g., in this request, we have `id=1`).\n\nA successful GET response will have a `200 OK` status, and should include some kind of response body - for example, HTML web content or JSON data."
			},
			"response": []
		},
		{
			"name": "GetLondonWeather (past)",
			"event": [
				{
					"listen": "test",
					"script": {
						"exec": [
							"pm.test(\"Status code is 200\", function () {",
							"    pm.response.to.have.status(200);",
							"});"
						],
						"type": "text/javascript",
						"packages": {}
					}
				}
			],
			"request": {
				"method": "GET",
				"header": [],
				"url": {
					"raw": "https://weather-api-07252024.azurewebsites.net/WeatherForecast?Date=07.18.2024&City=London&Country=United Kingdom",
					"protocol": "https",
					"host": [
						"weather-api-07252024",
						"azurewebsites",
						"net"
					],
					"path": [
						"WeatherForecast"
					],
					"query": [
						{
							"key": "Date",
							"value": "07.18.2024"
						},
						{
							"key": "City",
							"value": "London"
						},
						{
							"key": "Country",
							"value": "United Kingdom"
						}
					]
				},
				"description": "This is a GET request and it is used to \"get\" data from an endpoint. There is no request body for a GET request, but you can use query parameters to help specify the resource you want data on (e.g., in this request, we have `id=1`).\n\nA successful GET response will have a `200 OK` status, and should include some kind of response body - for example, HTML web content or JSON data."
			},
			"response": []
		},
		{
			"name": "GetWashingtonWeather",
			"event": [
				{
					"listen": "test",
					"script": {
						"exec": [
							"pm.test(\"Status code is 200\", function () {",
							"    pm.response.to.have.status(200);",
							"});"
						],
						"type": "text/javascript",
						"packages": {}
					}
				}
			],
			"request": {
				"method": "GET",
				"header": [],
				"url": {
					"raw": "https://weather-api-07252024.azurewebsites.net/WeatherForecast?Date=07.18.2024&City=Washington&Country=Unites States",
					"protocol": "https",
					"host": [
						"weather-api-07252024",
						"azurewebsites",
						"net"
					],
					"path": [
						"WeatherForecast"
					],
					"query": [
						{
							"key": "Date",
							"value": "07.18.2024"
						},
						{
							"key": "City",
							"value": "Washington"
						},
						{
							"key": "Country",
							"value": "Unites States"
						}
					]
				},
				"description": "This is a GET request and it is used to \"get\" data from an endpoint. There is no request body for a GET request, but you can use query parameters to help specify the resource you want data on (e.g., in this request, we have `id=1`).\n\nA successful GET response will have a `200 OK` status, and should include some kind of response body - for example, HTML web content or JSON data."
			},
			"response": []
		},
		{
			"name": "GetUkraineCityWeather",
			"event": [
				{
					"listen": "test",
					"script": {
						"exec": [
							"pm.test(\"Status code is 200\", function () {",
							"    pm.response.to.have.status(200);",
							"});"
						],
						"type": "text/javascript",
						"packages": {}
					}
				}
			],
			"request": {
				"method": "GET",
				"header": [],
				"url": {
					"raw": "https://weather-api-07252024.azurewebsites.net/WeatherForecast?Date=07.18.2024&City=Полтава&Country=Україна",
					"protocol": "https",
					"host": [
						"weather-api-07252024",
						"azurewebsites",
						"net"
					],
					"path": [
						"WeatherForecast"
					],
					"query": [
						{
							"key": "Date",
							"value": "07.18.2024"
						},
						{
							"key": "City",
							"value": "Полтава"
						},
						{
							"key": "Country",
							"value": "Україна"
						}
					]
				},
				"description": "This is a GET request and it is used to \"get\" data from an endpoint. There is no request body for a GET request, but you can use query parameters to help specify the resource you want data on (e.g., in this request, we have `id=1`).\n\nA successful GET response will have a `200 OK` status, and should include some kind of response body - for example, HTML web content or JSON data."
			},
			"response": []
		}
	],
	"event": [
		{
			"listen": "prerequest",
			"script": {
				"type": "text/javascript",
				"exec": [
					""
				]
			}
		},
		{
			"listen": "test",
			"script": {
				"type": "text/javascript",
				"exec": [
					""
				]
			}
		}
	],
	"variable": [
		{
			"key": "id",
			"value": "1"
		},
		{
			"key": "base_url",
			"value": "https://postman-rest-api-learner.glitch.me/"
		}
	]
}